{"cameraMode":{"drawMode":0,"name":"Shaded","section":"Shading Mode"},"sceneLighting":true,"audioPlay":false,"sceneViewState":{"m_AlwaysRefresh":false,"showFog":true,"showSkybox":true,"showFlares":true,"showImageEffects":true,"showParticleSystems":true,"showVisualEffectGraphs":true,"m_FxEnabled":true},"in2DMode":false,"pivot":{"x":456.7975158691406,"y":763.3610229492188,"z":-57.348419189453128},"rotation":{"x":-0.03630130738019943,"y":0.0020960948895663025,"z":-0.00008611389057477936,"w":-0.9993461966514587},"size":169.52871704101563,"orthographic":false}